emerge/__init__.py
emerge/abstractresult.py
emerge/analysis.py
emerge/analyzer.py
emerge/appear.py
emerge/config.py
emerge/core.py
emerge/export.py
emerge/files.py
emerge/graph.py
emerge/log.py
emerge/main.py
emerge/results.py
emerge/stats.py
emerge/configs/c-template.yaml
emerge/configs/cpp-template.yaml
emerge/configs/default.yaml
emerge/configs/emerge.yaml
emerge/configs/go-template.yaml
emerge/configs/groovy-template.yaml
emerge/configs/java-template.yaml
emerge/configs/javascript-template.yaml
emerge/configs/kotlin-template.yaml
emerge/configs/objc-template.yaml
emerge/configs/py-template.yaml
emerge/configs/ruby-template.yaml
emerge/configs/swift-template.yaml
emerge/configs/typescript-template.yaml
emerge/languages/__init__.py
emerge/languages/abstractparser.py
emerge/languages/cparser.py
emerge/languages/cppparser.py
emerge/languages/goparser.py
emerge/languages/groovyparser.py
emerge/languages/javaparser.py
emerge/languages/javascriptparser.py
emerge/languages/kotlinparser.py
emerge/languages/objcparser.py
emerge/languages/pyparser.py
emerge/languages/rubyparser.py
emerge/languages/swiftparser.py
emerge/languages/typescriptparser.py
emerge/metrics/__init__.py
emerge/metrics/abstractmetric.py
emerge/metrics/metrics.py
emerge/metrics/faninout/__init__.py
emerge/metrics/faninout/faninout.py
emerge/metrics/git/__init__.py
emerge/metrics/git/git.py
emerge/metrics/modularity/__init__.py
emerge/metrics/modularity/modularity.py
emerge/metrics/numberofmethods/__init__.py
emerge/metrics/numberofmethods/numberofmethods.py
emerge/metrics/sloc/__init__.py
emerge/metrics/sloc/sloc.py
emerge/metrics/tfidf/__init__.py
emerge/metrics/tfidf/tfidf.py
emerge/metrics/whitespace/__init__.py
emerge/metrics/whitespace/whitespace.py
emerge/myconfigs/c-template.yaml
emerge/myconfigs/cpp-template.yaml
emerge/myconfigs/default.yaml
emerge/myconfigs/emerge.yaml
emerge/myconfigs/go-template.yaml
emerge/myconfigs/groovy-template.yaml
emerge/myconfigs/java-template.yaml
emerge_viz-2.0.7.dist-info/LICENSE
emerge_viz-2.0.7.dist-info/METADATA
emerge_viz-2.0.7.dist-info/WHEEL
emerge_viz-2.0.7.dist-info/entry_points.txt
emerge_viz-2.0.7.dist-info/top_level.txt
emerge_viz-2.0.7.dist-info/RECORD
