Metadata-Version: 2.1
Name: emerge-viz
Version: 2.0.7
Summary: Visualize source code structure and dependencies in an interactive d3 application
Home-page: https://github.com/glato/emerge
Author: Grzegorz Lato
Author-email: grzegorz.lato@gmail.com
License: MIT
Classifier: License :: OSI Approved :: MIT License
Classifier: Programming Language :: Python :: 3
Classifier: Programming Language :: Python :: 3.8
License-File: LICENSE
Requires-Dist: wheel
Requires-Dist: autopep8
Requires-Dist: coloredlogs
Requires-Dist: interrogate
Requires-Dist: networkx
Requires-Dist: scikit-learn
Requires-Dist: numpy
Requires-Dist: prettytable
Requires-Dist: py
Requires-Dist: pycodestyle
Requires-Dist: pylint
Requires-Dist: pyparsing
Requires-Dist: python-louvain
Requires-Dist: PyYAML
Requires-Dist: tabulate
Requires-Dist: PyDriller
Requires-Dist: pyperclip
